[
  {
    "titulo": "El manga JM, del creador de Hinamatsuri, tendrá adaptación al anime",
    "imagen": "https://cdn.myanimelist.net/images/anime/1015/138006l.jpg",
    "link": "#"
  },
  {
    "titulo": "Revelan nuevo tráiler de la Temporada 3 de One Punch Man",
    "imagen": "https://cdn.myanimelist.net/images/anime/1806/126216l.jpg",
    "link": "#"
  },
  {
    "titulo": "Dragon Ball Daima anuncia su fecha de estreno mundial",
    "imagen": "https://cdn.myanimelist.net/images/anime/1005/139044l.jpg",
    "link": "#"
  }
]
